.DS_Store
broers_langchain/__init__.py
broers_langchain/text_splitter.py
broers_langchain/agents/__init__.py
broers_langchain/agents/chatglm_functions_agent/__init__.py
broers_langchain/agents/chatglm_functions_agent/base.py
broers_langchain/agents/chatglm_functions_agent/output_parser.py
broers_langchain/agents/chatglm_functions_agent/prompt.py
broers_langchain/agents/llm_functions_agent/__init__.py
broers_langchain/agents/llm_functions_agent/base.py
broers_langchain/autogen_role/__init__.py
broers_langchain/autogen_role/assistant.py
broers_langchain/autogen_role/custom.py
broers_langchain/autogen_role/groupchat_manager.py
broers_langchain/autogen_role/user.py
broers_langchain/chains/__init__.py
broers_langchain/chains/loader_output.py
broers_langchain/chains/transform.py
broers_langchain/chains/autogen/__init__.py
broers_langchain/chains/autogen/auto_gen.py
broers_langchain/chains/combine_documents/__init__.py
broers_langchain/chains/combine_documents/stuff.py
broers_langchain/chains/conversational_retrieval/__init__.py
broers_langchain/chains/conversational_retrieval/base.py
broers_langchain/chains/qa_generation/__init__.py
broers_langchain/chains/qa_generation/base.py
broers_langchain/chains/qa_generation/base_v2.py
broers_langchain/chains/qa_generation/prompt.py
broers_langchain/chains/qa_generation/prompt_v2.py
broers_langchain/chains/question_answering/__init__.py
broers_langchain/chains/retrieval/__init__.py
broers_langchain/chains/retrieval/retrieval_chain.py
broers_langchain/chains/retrieval_qa/__init__.py
broers_langchain/chains/retrieval_qa/base.py
broers_langchain/chains/router/__init__.py
broers_langchain/chains/router/multi_rule.py
broers_langchain/chains/router/rule_router.py
broers_langchain/chat_models/__init__.py
broers_langchain/chat_models/host_llm.py
broers_langchain/chat_models/minimax.py
broers_langchain/chat_models/proxy_llm.py
broers_langchain/chat_models/qwen.py
broers_langchain/chat_models/sensetime.py
broers_langchain-0.2.0.dist-info/METADATA
broers_langchain-0.2.0.dist-info/WHEEL
broers_langchain-0.2.0.dist-info/top_level.txt
broers_langchain-0.2.0.dist-info/RECORD
