Metadata-Version: 2.2
Name: broers_langchain
Version: 0.2.0
Summary: broers langchain modules
Home-page: https://e.coding.net/mydevtest/ai/broers_langchain
Author: Jaden
Author-email: jieabx@gmail.com
Classifier: Programming Language :: Python :: 3
Classifier: Programming Language :: Python :: 3.6
Classifier: Programming Language :: Python :: 3.7
Classifier: Programming Language :: Python :: 3.8
Classifier: Programming Language :: Python :: 3.9
Classifier: License :: OSI Approved :: Apache Software License
Classifier: Operating System :: OS Independent
Requires-Python: >=3.6
Requires-Dist: langchain==0.2.*
Requires-Dist: langchain-community==0.2.*
Requires-Dist: zhipuai~=1.0.7
Requires-Dist: websocket-client~=1.6.4
Requires-Dist: elasticsearch~=8.10.1
Requires-Dist: google-search-results~=2.4.1
Requires-Dist: google-api-python-client~=2.79.0
Requires-Dist: opencv-python==4.5.5.64
Requires-Dist: Pillow==9.5.0
Requires-Dist: bisheng-pyautogen
Requires-Dist: jieba==0.42.1
Requires-Dist: pydantic==1.10.*
Requires-Dist: pymupdf==1.23.8
Requires-Dist: shapely==2.0.2
Requires-Dist: filetype==1.2.0
Requires-Dist: langgraph==0.2.*
Requires-Dist: langchain_experimental
Requires-Dist: openai==1.51.*
Requires-Dist: langchain_openai>=0.1.25
Requires-Dist: llama-index==0.9.48
Requires-Dist: bisheng-ragas==1.*
Requires-Dist: pypdfium2
Requires-Dist: loguru
Requires-Dist: sympy
Requires-Dist: matplotlib
Requires-Dist: pymysql
Requires-Dist: pymilvus
Requires-Dist: torch
Requires-Dist: transformers
Requires-Dist: gradio
Requires-Dist: minio
Dynamic: author
Dynamic: author-email
Dynamic: classifier
Dynamic: description
Dynamic: description-content-type
Dynamic: home-page
Dynamic: requires-dist
Dynamic: requires-python
Dynamic: summary
